odoo8_addon_sql_request_abstract-8.0.1.0.0-py2.7-nspkg.pth
odoo_addons/sql_request_abstract/__openerp__.py
odoo_addons/sql_request_abstract/__init__.py
odoo_addons/sql_request_abstract/README.rst
odoo_addons/sql_request_abstract/security/res_groups.xml
odoo_addons/sql_request_abstract/security/ir_module_category.xml
odoo_addons/sql_request_abstract/security/ir.model.access.csv
odoo_addons/sql_request_abstract/models/sql_request_mixin.py
odoo_addons/sql_request_abstract/models/__init__.py
odoo_addons/sql_request_abstract/i18n/sql_export_abstract.pot
odoo_addons/sql_request_abstract/i18n/fr.po
odoo_addons/sql_request_abstract/static/description/icon.png
odoo8_addon_sql_request_abstract-8.0.1.0.0.dist-info/top_level.txt
odoo8_addon_sql_request_abstract-8.0.1.0.0.dist-info/WHEEL
odoo8_addon_sql_request_abstract-8.0.1.0.0.dist-info/RECORD
odoo8_addon_sql_request_abstract-8.0.1.0.0.dist-info/metadata.json
odoo8_addon_sql_request_abstract-8.0.1.0.0.dist-info/DESCRIPTION.rst
odoo8_addon_sql_request_abstract-8.0.1.0.0.dist-info/METADATA
odoo8_addon_sql_request_abstract-8.0.1.0.0.dist-info/namespace_packages.txt
